MANIFEST.in
setup.py
PyHAML.egg-info/PKG-INFO
PyHAML.egg-info/SOURCES.txt
PyHAML.egg-info/dependency_links.txt
PyHAML.egg-info/requires.txt
PyHAML.egg-info/top_level.txt
haml/__init__.py
haml/codegen.py
haml/filters.py
haml/nodes.py
haml/parse.py
haml/runtime.py
haml/util.py
scripts/haml-preprocess
scripts/haml-render
tests/base.py
tests/test_conformance.py
tests/test_mako.py
tests/test_mixins.py
tests/test_pythonisms.py